huoguoml/__init__.py
huoguoml/cli.py
huoguoml/constants.py
huoguoml/dashboard/build/apple-touch-icon.png
huoguoml/dashboard/build/asset-manifest.json
huoguoml/dashboard/build/favicon.ico
huoguoml/dashboard/build/index.html.orig
huoguoml/dashboard/build/logo192.png
huoguoml/dashboard/build/logo512.png
huoguoml/dashboard/build/manifest.json
huoguoml/dashboard/build/robots.txt
huoguoml/dashboard/build/static/css/5.63787aad.chunk.css
huoguoml/dashboard/build/static/css/9.e6924ae7.chunk.css
huoguoml/dashboard/build/static/css/main.23a98057.chunk.css
huoguoml/dashboard/build/static/js/0.871fefe4.chunk.js
huoguoml/dashboard/build/static/js/1.a27e8926.chunk.js
huoguoml/dashboard/build/static/js/10.c4bacc8e.chunk.js
huoguoml/dashboard/build/static/js/10.c4bacc8e.chunk.js.LICENSE.txt
huoguoml/dashboard/build/static/js/11.11e99ea6.chunk.js
huoguoml/dashboard/build/static/js/11.11e99ea6.chunk.js.LICENSE.txt
huoguoml/dashboard/build/static/js/12.04e111de.chunk.js
huoguoml/dashboard/build/static/js/13.961d747c.chunk.js
huoguoml/dashboard/build/static/js/14.eae52016.chunk.js
huoguoml/dashboard/build/static/js/15.0e81d5a6.chunk.js
huoguoml/dashboard/build/static/js/16.5153fd6d.chunk.js
huoguoml/dashboard/build/static/js/17.76204f01.chunk.js
huoguoml/dashboard/build/static/js/18.77860266.chunk.js
huoguoml/dashboard/build/static/js/18.77860266.chunk.js.LICENSE.txt
huoguoml/dashboard/build/static/js/19.497c1417.chunk.js
huoguoml/dashboard/build/static/js/2.7a747ccb.chunk.js
huoguoml/dashboard/build/static/js/20.ccff44f0.chunk.js
huoguoml/dashboard/build/static/js/21.33a7bb55.chunk.js
huoguoml/dashboard/build/static/js/22.0968ed8e.chunk.js
huoguoml/dashboard/build/static/js/23.1e95be38.chunk.js
huoguoml/dashboard/build/static/js/24.122ddde6.chunk.js
huoguoml/dashboard/build/static/js/25.15a71170.chunk.js
huoguoml/dashboard/build/static/js/26.fc681df6.chunk.js
huoguoml/dashboard/build/static/js/27.4abd604a.chunk.js
huoguoml/dashboard/build/static/js/28.dd5905f3.chunk.js
huoguoml_dev-1624482273.dist-info/LICENSE
huoguoml_dev-1624482273.dist-info/METADATA
huoguoml_dev-1624482273.dist-info/WHEEL
huoguoml_dev-1624482273.dist-info/entry_points.txt
huoguoml_dev-1624482273.dist-info/top_level.txt
huoguoml_dev-1624482273.dist-info/RECORD
