Metadata-Version: 2.1
Name: huoguoml-dev
Version: 1624482273
Summary: A platform for managing and serving Machine Learning types.
Home-page: https://huoguoml.github.io
Author: Steven Mi
License: Apache 2.0
Keywords: HuoguoML
Platform: UNKNOWN
Classifier: Development Status :: 5 - Production/Stable
Classifier: Intended Audience :: Developers
Classifier: Intended Audience :: Education
Classifier: Intended Audience :: Science/Research
Classifier: Programming Language :: Python :: 3.7
Classifier: Programming Language :: Python :: 3.8
Classifier: Programming Language :: Python :: 3.9
Classifier: Programming Language :: Unix Shell
Classifier: Environment :: Console
Classifier: License :: OSI Approved :: Apache Software License
Classifier: Operating System :: OS Independent
Classifier: Topic :: Database :: Database Engines/Servers
Classifier: Topic :: Scientific/Engineering :: Artificial Intelligence
Classifier: Topic :: Software Development
Classifier: Topic :: Software Development :: Libraries
Classifier: Topic :: Software Development :: Libraries :: Python Modules
Requires-Python: >=3.7.*
Requires-Dist: sqlalchemy
Requires-Dist: aiofiles
Requires-Dist: python-multipart
Requires-Dist: click
Requires-Dist: pyyaml
Requires-Dist: pytest
Requires-Dist: fastapi (>=0.65)
Requires-Dist: requests
Requires-Dist: uvicorn
Provides-Extra: aiofiles
Requires-Dist: aiofiles ; extra == 'aiofiles'
Provides-Extra: all
Requires-Dist: sqlalchemy ; extra == 'all'
Requires-Dist: aiofiles ; extra == 'all'
Requires-Dist: python-multipart ; extra == 'all'
Requires-Dist: click ; extra == 'all'
Requires-Dist: pyyaml ; extra == 'all'
Requires-Dist: pytest ; extra == 'all'
Requires-Dist: fastapi (>=0.65) ; extra == 'all'
Requires-Dist: requests ; extra == 'all'
Requires-Dist: uvicorn ; extra == 'all'
Provides-Extra: click
Requires-Dist: click ; extra == 'click'
Provides-Extra: dev
Requires-Dist: sqlalchemy ; extra == 'dev'
Requires-Dist: aiofiles ; extra == 'dev'
Requires-Dist: requests ; extra == 'dev'
Requires-Dist: python-multipart ; extra == 'dev'
Requires-Dist: click ; extra == 'dev'
Requires-Dist: pyyaml ; extra == 'dev'
Requires-Dist: fastapi (>=0.65) ; extra == 'dev'
Requires-Dist: uvicorn ; extra == 'dev'
Provides-Extra: fastapi
Requires-Dist: fastapi (>=0.65) ; extra == 'fastapi'
Provides-Extra: pytest
Requires-Dist: pytest ; extra == 'pytest'
Provides-Extra: python-multipart
Requires-Dist: python-multipart ; extra == 'python-multipart'
Provides-Extra: pyyaml
Requires-Dist: pyyaml ; extra == 'pyyaml'
Provides-Extra: requests
Requires-Dist: requests ; extra == 'requests'
Provides-Extra: sqlalchemy
Requires-Dist: sqlalchemy ; extra == 'sqlalchemy'
Provides-Extra: test
Requires-Dist: pytest ; extra == 'test'
Provides-Extra: uvicorn
Requires-Dist: uvicorn ; extra == 'uvicorn'
